datacol/__init__.py
datacol/__main__.py
datacol-1.1.0.dist-info/DESCRIPTION.rst
datacol-1.1.0.dist-info/METADATA
datacol-1.1.0.dist-info/RECORD
datacol-1.1.0.dist-info/WHEEL
datacol-1.1.0.dist-info/metadata.json
datacol-1.1.0.dist-info/top_level.txt
