Metadata-Version: 2.0
Name: datacol
Version: 1.1.0
Summary: Localized, file-based database module.
Home-page: https://github.com/EKHolmes/DataCol/
Author: Erik Holmes
Author-email: zv.eevee6718@gmail.com
License: MIT
Platform: UNKNOWN
Classifier: License :: OSI Approved :: MIT License
Classifier: Programming Language :: Python :: 3
Classifier: Programming Language :: Python :: 3.8
